isb_miner2-0.2.8.data/scripts/miner2-bcmembers
isb_miner2-0.2.8.data/scripts/miner2-causalinf-post
isb_miner2-0.2.8.data/scripts/miner2-causalinf-pre
isb_miner2-0.2.8.data/scripts/miner2-causalinference
isb_miner2-0.2.8.data/scripts/miner2-coexpr
isb_miner2-0.2.8.data/scripts/miner2-mechinf
isb_miner2-0.2.8.data/scripts/miner2-neo
isb_miner2-0.2.8.data/scripts/miner2-riskpredict
isb_miner2-0.2.8.data/scripts/miner2-subtypes
isb_miner2-0.2.8.data/scripts/miner2-survival
isb_miner2-0.2.8.dist-info/DESCRIPTION.rst
isb_miner2-0.2.8.dist-info/METADATA
isb_miner2-0.2.8.dist-info/RECORD
isb_miner2-0.2.8.dist-info/WHEEL
isb_miner2-0.2.8.dist-info/metadata.json
isb_miner2-0.2.8.dist-info/top_level.txt
miner2/__init__.py
miner2/biclusters.py
miner2/causal_inference.py
miner2/coexpression.py
miner2/mechanistic_inference.py
miner2/miner.py
miner2/preprocess.py
miner2/risk_predict.py
miner2/subtypes.py
miner2/survival.py
miner2/util.py
miner2/data/all_tfs_to_motifs.pkl
miner2/data/identifier_mappings.txt
miner2/data/tfbsdb_tf_to_genes.pkl
