Metadata-Version: 2.0
Name: isb-miner2
Version: 0.2.8
Summary: A newer version of MINER.
Home-page: https://github.com/baliga-lab/miner2
Author: Adrian Lopez Garcia de Lomana
Author-email: alomana@systemsbiology.org
License: UNKNOWN
Platform: UNKNOWN
Classifier: Development Status :: 5 - Production/Stable
Classifier: Environment :: Console
Classifier: Intended Audience :: Science/Research
Classifier: Natural Language :: English
Classifier: License :: OSI Approved :: GNU General Public License v3 or later (GPLv3+)
Classifier: Operating System :: OS Independent
Classifier: Programming Language :: Python
Classifier: Programming Language :: Python :: 2
Classifier: Programming Language :: Python :: 2.7
Classifier: Programming Language :: Python
Classifier: Programming Language :: Python :: 3
Classifier: Programming Language :: Python :: 3.6
Classifier: Topic :: Scientific/Engineering :: Bio-Informatics
Classifier: Topic :: Software Development :: Libraries :: Python Modules
Requires-Dist: numpy
Requires-Dist: scipy
Requires-Dist: pandas
Requires-Dist: sklearn
Requires-Dist: lifelines
Requires-Dist: matplotlib
Requires-Dist: seaborn
Requires-Dist: pydot
Requires-Dist: graphviz
